LD2410/LICENSE
LD2410/__init__.py
LD2410/ld2410.py
LD2410/ld2410_consts.py
LD2410/setup.py
ld2410-1.1.1.dist-info/METADATA
ld2410-1.1.1.dist-info/WHEEL
ld2410-1.1.1.dist-info/licenses/LICENSE
ld2410-1.1.1.dist-info/RECORD
