Metadata-Version: 2.1
Name: LD2410
Version: 1.1.1
Summary: A python interface for the HiLink LD2410 presence detection module
Project-URL: Homepage, https://github.com/vjsyong/LD2410
Author-email: Vi Jun Sean Yong <vjsyong@connect.ust.hk>
License-File: LICENSE
Classifier: License :: OSI Approved :: MIT License
Classifier: Operating System :: OS Independent
Classifier: Programming Language :: Python :: 3
Requires-Python: >=3.8
